{
    "data": {
        "type": "message",
        "attributes": {
            "code": "2020-08-19-2",
            "content": "<p>Hi guys! We're sorry but tomorrow afternoon we've to close the exchange point because Bob got sick.</p><p>Remember that thursday we'll open at 10AM in the morning!</p>",
            "images": [],
            "access": "public"
        },
        "relationships": {
            "author": {
                "data": {
                    "type": "members",
                    "id": "9683ec5d-29d3-419a-8753-a5d092f1bb3d"
                }
            }
        }
    }
}